CS666_A2/Q1/euclidean.v
module extended_euclidean(a, b, out, clk, rst);
	input signed [32:1] a, b;
	input clk, rst;
	output reg signed [32:1] out; 
	
	reg signed [32:1] u, v, w, x, y, z;
	reg [4:1] state, nxtstate;
	reg [32:1] temp, w_prev, x_prev, y_prev, z_prev;
	
	parameter state0 = 4'h0, state1 = 4'h1, state2 = 4'h2, statte3 = 4'h3;
	parameter state4 = 4'h4, state5 = 4'h5, state6 = 4'h6, state7 = 4'h7;
	
	always @ (posedge clk or posedge rst)
	begin
		if(rst)
		begin
			state <= state0;
			u <= a; v <= b;
			w <= 1; x <= 0; y <= 0; z <= 1;
		end
		else
			state = nxtstate;
	end
	
	always @ (*)
	begin
		case (state)
			state0:
				if(u != 0)
					nxtstate = state1;
				else
					nxtstate = state6;
			
			state1:
				begin
					if(u[0] == 1'b0)
						nxtstate = state2;
					else
						nxtstate = statte3;
				end
				
			state2:
				begin
					u = u >>> 1;
					if(w[0] == 1'b0 && x[0] == 1'b0)
					begin
						w_prev = w;
						w = w >>> 1;
						x_prev = x;
						x = x >>> 1;
						if(w_prev == w)
							w = 0;
						else 
							w = w;
						if(x_prev == x)
							x = 0;
						else
							x = x;
					end
					else
					begin
						w_prev = w + b;
						w = (w + b) >>> 1;
						x_prev = x - a;
						x = (x - a) >>> 1;
						if(w_prev == w) 
							w = 0;
						else 
							w = w;
						if(x_prev == x)
							x = 0;
						else
							x = x;
					end
					nxtstate = state1;
				end
				
			statte3:
				begin
					if(v[0] == 1'b0)
						nxtstate = state4;
					else
						nxtstate = state5;
				end
				
			state4:
				begin
					v = v >>> 1;
					if(y[0] == 1'b0 && z[0] == 1'b0)
					begin
						y_prev = y;
						y = y >>> 1;
						z_prev = z;
						z = z >>> 1;
						if(y_prev == y)
							y = 0;
						else 
							y = y;
						if(z_prev == z)
							z = 0;
						else
							z = z;
					end
					else
					begin
						y_prev = y + b;
						y = (y + b) >>> 1;
						z_prev = z - a;
						z = (z - a) >>> 1;
						if(y_prev == y)
							y = 0;
						else
							y = y;
						if(z_prev == z)
							z = 0;
						else
							z = z;
					end
					nxtstate = statte3;
				end
				
			state5:
				begin
					if(u >= v)
					begin
						u = u - v;
						w = w - y;
						x = x - z;
					end
					else
					begin
						v = v - u;
						y = y - w;
						z = z - x;
					end
					nxtstate = state0;
				end
				
			state6:
				begin
					if(y[31] == 1'b1)
					begin
						temp = (b - y) % b;
						out = b - temp;
					end
					else
						out = y % b;
					nxtstate = state7;
					end
					
			state7: ; //do nothing
			
			default: nxtstate = state0;
		endcase
	end
	
endmodule

CS666_A2/Q1/testbench.v
`timescale 1ns/1ns

module testbench();
	reg signed [32:1] a, b;
	reg clk, rst;
	wire signed [32:1] out; 
	
	integer i;
	extended_euclidean dut(a, b, out, clk, rst);
	
	initial
	begin
		$dumpfile("euclidean.vcd");
    	$dumpvars(0, testbench);
		a = 719;
		b = 9001;
		
		clk = 0; rst = 0; #5;
		
		for(i = 1; i <= 999; i++)
		begin
			if(i == 1)
				rst = 1;
			else
				rst = 0;
			clk = 1; #5; clk = ~clk; #5;
			if(out != 0)
			begin
				$display(out);
				$finish;
			end
		end
	end
	
endmodule

CS666_A2/Q1/euclidean.vcd
$date
	Sun Sep 04 17:41:56 2022
$end
$version
	Icarus Verilog
$end
$timescale
	1ns
$end
$scope module testbench $end
$var wire 32 ! out [32:1] $end
$var reg 32 " a [32:1] $end
$var reg 32 # b [32:1] $end
$var reg 1 $ clk $end
$var reg 1 % rst $end
$var integer 32 & i [31:0] $end
$scope module dut $end
$var wire 32 ' a [32:1] $end
$var wire 32 ( b [32:1] $end
$var wire 1 $ clk $end
$var wire 1 % rst $end
$var parameter 4 ) state0 $end
$var parameter 4 * state1 $end
$var parameter 4 + state2 $end
$var parameter 4 , state4 $end
$var parameter 4 - state5 $end
$var parameter 4 . state6 $end
$var parameter 4 / state7 $end
$var parameter 4 0 statte3 $end
$var reg 4 1 nxtstate [4:1] $end
$var reg 32 2 out [32:1] $end
$var reg 4 3 state [4:1] $end
$var reg 32 4 temp [32:1] $end
$var reg 32 5 u [32:1] $end
$var reg 32 6 v [32:1] $end
$var reg 32 7 w [32:1] $end
$var reg 32 8 w_prev [32:1] $end
$var reg 32 9 x [32:1] $end
$var reg 32 : x_prev [32:1] $end
$var reg 32 ; y [32:1] $end
$var reg 32 < y_prev [32:1] $end
$var reg 32 = z [32:1] $end
$var reg 32 > z_prev [32:1] $end
$upscope $end
$upscope $end
$enddefinitions $end
$comment Show the parameter values. $end
$dumpall
b11 0
b111 /
b110 .
b101 -
b100 ,
b10 +
b1 *
b0 )
$end
#0
$dumpvars
bx >
bx =
bx <
bx ;
bx :
bx 9
bx 8
bx 7
bx 6
bx 5
bx 4
bx 3
bx 2
b0 1
b10001100101001 (
b1011001111 '
bx &
0%
0$
b10001100101001 #
b1011001111 "
bx !
$end
#5
b1 1
b1 =
b0 ;
b0 9
b1 7
b10001100101001 6
b1011001111 5
b0 3
1$
1%
b1 &
#10
0$
#15
b11 1
b1 3
1$
0%
b10 &
#20
0$
#25
b101 1
b11 3
1$
b11 &
#30
0$
#35
b0 1
b11111111111111111111111111111111 ;
b10000001011010 6
b101 3
1$
b100 &
#40
0$
#45
b1 1
b0 3
1$
b101 &
#50
0$
#55
b11 1
b1 3
1$
b110 &
#60
0$
#65
b101 1
b11 3
1$
b111 &
#70
0$
#75
b0 1
b11111111111111111111111111111110 ;
b1110110001011 6
b101 3
1$
b1000 &
#80
0$
#85
b1 1
b0 3
1$
b1001 &
#90
0$
#95
b11 1
b1 3
1$
b1010 &
#100
0$
#105
b101 1
b11 3
1$
b1011 &
#110
0$
#115
b0 1
b11111111111111111111111111111101 ;
b1101010111100 6
b101 3
1$
b1100 &
#120
0$
#125
b1 1
b0 3
1$
b1101 &
#130
0$
#135
b11 1
b1 3
1$
b1110 &
#140
0$
#145
b101 1
b11 3
1$
b1111 &
#150
0$
#155
b0 1
b11111111111111111111111111111100 ;
b1011111101101 6
b101 3
1$
b10000 &
#160
0$
#165
b1 1
b0 3
1$
b10001 &
#170
0$
#175
b11 1
b1 3
1$
b10010 &
#180
0$
#185
b101 1
b11 3
1$
b10011 &
#190
0$
#195
b0 1
b11111111111111111111111111111011 ;
b1010100011110 6
b101 3
1$
b10100 &
#200
0$
#205
b1 1
b0 3
1$
b10101 &
#210
0$
#215
b11 1
b1 3
1$
b10110 &
#220
0$
#225
b101 1
b11 3
1$
b10111 &
#230
0$
#235
b0 1
b11111111111111111111111111111010 ;
b1001001001111 6
b101 3
1$
b11000 &
#240
0$
#245
b1 1
b0 3
1$
b11001 &
#250
0$
#255
b11 1
b1 3
1$
b11010 &
#260
0$
#265
b101 1
b11 3
1$
b11011 &
#270
0$
#275
b0 1
b11111111111111111111111111111001 ;
b111110000000 6
b101 3
1$
b11100 &
#280
0$
#285
b1 1
b0 3
1$
b11101 &
#290
0$
#295
b11 1
b1 3
1$
b11110 &
#300
0$
#305
b101 1
b11 3
1$
b11111 &
#310
0$
#315
b0 1
b11111111111111111111111111111000 ;
b110010110001 6
b101 3
1$
b100000 &
#320
0$
#325
b1 1
b0 3
1$
b100001 &
#330
0$
#335
b11 1
b1 3
1$
b100010 &
#340
0$
#345
b101 1
b11 3
1$
b100011 &
#350
0$
#355
b0 1
b11111111111111111111111111110111 ;
b100111100010 6
b101 3
1$
b100100 &
#360
0$
#365
b1 1
b0 3
1$
b100101 &
#370
0$
#375
b11 1
b1 3
1$
b100110 &
#380
0$
#385
b101 1
b11 3
1$
b100111 &
#390
0$
#395
b0 1
b11111111111111111111111111110110 ;
b11100010011 6
b101 3
1$
b101000 &
#400
0$
#405
b1 1
b0 3
1$
b101001 &
#410
0$
#415
b11 1
b1 3
1$
b101010 &
#420
0$
#425
b101 1
b11 3
1$
b101011 &
#430
0$
#435
b0 1
b11111111111111111111111111110101 ;
b10001000100 6
b101 3
1$
b101100 &
#440
0$
#445
b1 1
b0 3
1$
b101101 &
#450
0$
#455
b11 1
b1 3
1$
b101110 &
#460
0$
#465
b101 1
b11 3
1$
b101111 &
#470
0$
#475
b0 1
b11111111111111111111111111110100 ;
b101110101 6
b101 3
1$
b110000 &
#480
0$
#485
b1 1
b0 3
1$
b110001 &
#490
0$
#495
b11 1
b1 3
1$
b110010 &
#500
0$
#505
b101 1
b11 3
1$
b110011 &
#510
0$
#515
b0 1
b11111111111111111111111111111111 9
b1101 7
b101011010 5
b101 3
1$
b110100 &
#520
0$
#525
b1 1
b0 3
1$
b110101 &
#530
0$
#535
b11 1
b1 3
1$
b110110 &
#540
0$
#545
b101 1
b11 3
1$
b110111 &
#550
0$
#555
b0 1
b10 =
b11111111111111111111111111100111 ;
b11011 6
b101 3
1$
b111000 &
#560
0$
#565
b1 1
b0 3
1$
b111001 &
#570
0$
#575
b11 1
b1 3
1$
b111010 &
#580
0$
#585
b101 1
b11 3
1$
b111011 &
#590
0$
#595
b0 1
b11111111111111111111111111111101 9
b100110 7
b100111111 5
b101 3
1$
b111100 &
#600
0$
#605
b1 1
b0 3
1$
b111101 &
#610
0$
#615
b11 1
b1 3
1$
b111110 &
#620
0$
#625
b101 1
b11 3
1$
b111111 &
#630
0$
#635
b0 1
b11111111111111111111111111111011 9
b111111 7
b100100100 5
b101 3
1$
b1000000 &
#640
0$
#645
b1 1
b0 3
1$
b1000001 &
#650
0$
#655
b11 1
b1 3
1$
b1000010 &
#660
0$
#665
b101 1
b11 3
1$
b1000011 &
#670
0$
#675
b0 1
b11111111111111111111111111111001 9
b1011000 7
b100001001 5
b101 3
1$
b1000100 &
#680
0$
#685
b1 1
b0 3
1$
b1000101 &
#690
0$
#695
b11 1
b1 3
1$
b1000110 &
#700
0$
#705
b101 1
b11 3
1$
b1000111 &
#710
0$
#715
b0 1
b11111111111111111111111111110111 9
b1110001 7
b11101110 5
b101 3
1$
b1001000 &
#720
0$
#725
b1 1
b0 3
1$
b1001001 &
#730
0$
#735
b11 1
b1 3
1$
b1001010 &
#740
0$
#745
b101 1
b11 3
1$
b1001011 &
#750
0$
#755
b0 1
b11111111111111111111111111110101 9
b10001010 7
b11010011 5
b101 3
1$
b1001100 &
#760
0$
#765
b1 1
b0 3
1$
b1001101 &
#770
0$
#775
b11 1
b1 3
1$
b1001110 &
#780
0$
#785
b101 1
b11 3
1$
b1001111 &
#790
0$
#795
b0 1
b11111111111111111111111111110011 9
b10100011 7
b10111000 5
b101 3
1$
b1010000 &
#800
0$
#805
b1 1
b0 3
1$
b1010001 &
#810
0$
#815
b11 1
b1 3
1$
b1010010 &
#820
0$
#825
b101 1
b11 3
1$
b1010011 &
#830
0$
#835
b0 1
b11111111111111111111111111110001 9
b10111100 7
b10011101 5
b101 3
1$
b1010100 &
#840
0$
#845
b1 1
b0 3
1$
b1010101 &
#850
0$
#855
b11 1
b1 3
1$
b1010110 &
#860
0$
#865
b101 1
b11 3
1$
b1010111 &
#870
0$
#875
b0 1
b11111111111111111111111111101111 9
b11010101 7
b10000010 5
b101 3
1$
b1011000 &
#880
0$
#885
b1 1
b0 3
1$
b1011001 &
#890
0$
#895
b11 1
b1 3
1$
b1011010 &
#900
0$
#905
b101 1
b11 3
1$
b1011011 &
#910
0$
#915
b0 1
b11111111111111111111111111101101 9
b11101110 7
b1100111 5
b101 3
1$
b1011100 &
#920
0$
#925
b1 1
b0 3
1$
b1011101 &
#930
0$
#935
b11 1
b1 3
1$
b1011110 &
#940
0$
#945
b101 1
b11 3
1$
b1011111 &
#950
0$
#955
b0 1
b11111111111111111111111111101011 9
b100000111 7
b1001100 5
b101 3
1$
b1100000 &
#960
0$
#965
b1 1
b0 3
1$
b1100001 &
#970
0$
#975
b11 1
b1 3
1$
b1100010 &
#980
0$
#985
b101 1
b11 3
1$
b1100011 &
#990
0$
#995
b0 1
b11111111111111111111111111101001 9
b100100000 7
b110001 5
b101 3
1$
b1100100 &
#1000
0$
#1005
b1 1
b0 3
1$
b1100101 &
#1010
0$
#1015
b11 1
b1 3
1$
b1100110 &
#1020
0$
#1025
b101 1
b11 3
1$
b1100111 &
#1030
0$
#1035
b0 1
b11111111111111111111111111100111 9
b100111001 7
b10110 5
b101 3
1$
b1101000 &
#1040
0$
#1045
b1 1
b0 3
1$
b1101001 &
#1050
0$
#1055
b11 1
b1 3
1$
b1101010 &
#1060
0$
#1065
b101 1
b11 3
1$
b1101011 &
#1070
0$
#1075
b0 1
b11011 =
b11111111111111111111111010101110 ;
b101 6
b101 3
1$
b1101100 &
#1080
0$
#1085
b1 1
b0 3
1$
b1101101 &
#1090
0$
#1095
b11 1
b1 3
1$
b1101110 &
#1100
0$
#1105
b101 1
b11 3
1$
b1101111 &
#1110
0$
#1115
b0 1
b11111111111111111111111111001100 9
b1010001011 7
b10001 5
b101 3
1$
b1110000 &
#1120
0$
#1125
b1 1
b0 3
1$
b1110001 &
#1130
0$
#1135
b11 1
b1 3
1$
b1110010 &
#1140
0$
#1145
b101 1
b11 3
1$
b1110011 &
#1150
0$
#1155
b0 1
b11111111111111111111111110110001 9
b1111011101 7
b1100 5
b101 3
1$
b1110100 &
#1160
0$
#1165
b1 1
b0 3
1$
b1110101 &
#1170
0$
#1175
b11 1
b1 3
1$
b1110110 &
#1180
0$
#1185
b101 1
b11 3
1$
b1110111 &
#1190
0$
#1195
b0 1
b11111111111111111111111110010110 9
b10100101111 7
b111 5
b101 3
1$
b1111000 &
#1200
0$
#1205
b1 1
b0 3
1$
b1111001 &
#1210
0$
#1215
b11 1
b1 3
1$
b1111010 &
#1220
0$
#1225
b101 1
b11 3
1$
b1111011 &
#1230
0$
#1235
b0 1
b11111111111111111111111101111011 9
b11010000001 7
b10 5
b101 3
1$
b1111100 &
#1240
0$
#1245
b1 1
b0 3
1$
b1111101 &
#1250
0$
#1255
b11 1
b1 3
1$
b1111110 &
#1260
0$
#1265
b101 1
b11 3
1$
b1111111 &
#1270
0$
#1275
b0 1
b10100000 =
b11111111111111111111100000101101 ;
b11 6
b101 3
1$
b10000000 &
#1280
0$
#1285
b1 1
b0 3
1$
b10000001 &
#1290
0$
#1295
b11 1
b1 3
1$
b10000010 &
#1300
0$
#1305
b101 1
b11 3
1$
b10000011 &
#1310
0$
#1315
b0 1
b100100101 =
b11111111111111111111000110101100 ;
b1 6
b101 3
1$
b10000100 &
#1320
0$
#1325
b1 1
b0 3
1$
b10000101 &
#1330
0$
#1335
b11 1
b1 3
1$
b10000110 &
#1340
0$
#1345
b101 1
b11 3
1$
b10000111 &
#1350
0$
#1355
b0 1
b11111111111111111111111001010110 9
b1010011010101 7
b1 5
b101 3
1$
b10001000 &
#1360
0$
#1365
b1 1
b0 3
1$
b10001001 &
#1370
0$
#1375
b11 1
b1 3
1$
b10001010 &
#1380
0$
#1385
b101 1
b11 3
1$
b10001011 &
#1390
0$
#1395
b0 1
b11111111111111111111110100110001 9
b10001100101001 7
b0 5
b101 3
1$
b10001100 &
#1400
0$
#1405
b110 1
b0 3
1$
b10001101 &
#1410
0$
#1415
b111 1
b1010011010101 !
b1010011010101 2
b111001010100 4
b110 3
1$
b10001110 &
