CS666_A2/Q2/a/present.v
`timescale 1ns / 1ns

module present(x, s);
    input [3:0] x;
    output reg [3:0] s;

    always @ (x)
    begin
	case (x)
        0: s = 12;
        1: s = 5;
        2: s = 6;
        3: s = 11;
        4: s = 9;
        5: s = 0;
        6: s = 10;
        7: s = 13;
        8: s = 3;
        9: s = 14;
        10: s = 15;
        11: s = 8;
        12: s = 4;
        13: s = 7;
        14: s = 1;
        15: s = 2;
	endcase
    end
endmodule

CS666_A2/Q2/a/present-test.v
module testbench;



reg [3:0] x;
wire [3:0] s;
present DUT(x, s);

initial 
begin
    $dumpfile("present.vcd");
    $dumpvars(0, testbench);
    $monitor ("x=%h, s=%h", x, s);
    #5 x=4'b0000; 
    #5 x=4'b0001; 
    #5 x=4'b0010;
    #5 x=4'b0011; 
    #5 x=4'b0100; 
    #5 x=4'b0101;
    #5 x=4'b0110; 
    #5 x=4'b0111; 
    #5 x=4'b1000;
    #5 x=4'b1001; 
    #5 x=4'b1010; 
    #5 x=4'b1011;
    #5 x=4'b1100; 
    #5 x=4'b1101; 
    #5 x=4'b1110; 
    #5 x=4'b1111; 
    #5 $finish;
end

endmodule

CS666_A2/Q2/a/present.vcd
$date
	Sun Sep 04 16:07:22 2022
$end
$version
	Icarus Verilog
$end
$timescale
	1ns
$end
$scope module testbench $end
$var wire 4 ! s [3:0] $end
$var reg 4 " x [3:0] $end
$scope module DUT $end
$var wire 4 # x [3:0] $end
$var reg 4 $ s [3:0] $end
$upscope $end
$upscope $end
$enddefinitions $end
$comment Show the parameter values. $end
$dumpall
$end
#0
$dumpvars
bx $
bx #
bx "
bx !
$end
#5
b1100 !
b1100 $
b0 "
b0 #
#10
b101 !
b101 $
b1 "
b1 #
#15
b110 !
b110 $
b10 "
b10 #
#20
b1011 !
b1011 $
b11 "
b11 #
#25
b1001 !
b1001 $
b100 "
b100 #
#30
b0 !
b0 $
b101 "
b101 #
#35
b1010 !
b1010 $
b110 "
b110 #
#40
b1101 !
b1101 $
b111 "
b111 #
#45
b11 !
b11 $
b1000 "
b1000 #
#50
b1110 !
b1110 $
b1001 "
b1001 #
#55
b1111 !
b1111 $
b1010 "
b1010 #
#60
b1000 !
b1000 $
b1011 "
b1011 #
#65
b100 !
b100 $
b1100 "
b1100 #
#70
b111 !
b111 $
b1101 "
b1101 #
#75
b1 !
b1 $
b1110 "
b1110 #
#80
b10 !
b10 $
b1111 "
b1111 #
